nntoolkit/__init__.py
nntoolkit/activation_functions.py
nntoolkit/cli.py
nntoolkit/create.py
nntoolkit/evaluate.py
nntoolkit/test.py
nntoolkit/train.py
nntoolkit/utils.py
nntoolkit-0.2.2.dist-info/LICENSE
nntoolkit-0.2.2.dist-info/METADATA
nntoolkit-0.2.2.dist-info/WHEEL
nntoolkit-0.2.2.dist-info/entry_points.txt
nntoolkit-0.2.2.dist-info/top_level.txt
nntoolkit-0.2.2.dist-info/RECORD
