Metadata-Version: 2.1
Name: nntoolkit
Version: 0.2.2
Summary: Neural Network Toolkit
Home-page: https://github.com/MartinThoma/nntoolkit
Author: Martin Thoma
Author-email: info@martin-thoma.de
Maintainer: Martin Thoma
Maintainer-email: info@martin-thoma.de
License: MIT
Download-URL: https://github.com/MartinThoma/nntoolkit
Keywords: Neural Networks,Feed-Forward,NN,MLP
Platform: Linux
Platform: MacOS X
Platform: Windows
Classifier: Development Status :: 7 - Inactive
Classifier: Environment :: Console
Classifier: Intended Audience :: Developers
Classifier: Intended Audience :: Science/Research
Classifier: License :: OSI Approved :: MIT License
Classifier: Natural Language :: English
Classifier: Programming Language :: Python :: 3
Classifier: Programming Language :: Python :: 3 :: Only
Classifier: Programming Language :: Python :: 3.6
Classifier: Programming Language :: Python :: 3.7
Classifier: Programming Language :: Python :: 3.8
Classifier: Topic :: Scientific/Engineering :: Artificial Intelligence
Classifier: Topic :: Software Development
Classifier: Topic :: Utilities
Requires-Python: >= 3.0
Requires-Dist: argparse
Requires-Dist: Cython
Requires-Dist: h5py
Requires-Dist: keras
Requires-Dist: natsort
Requires-Dist: numpy
Requires-Dist: pytest
Requires-Dist: PyYAML
